daemoncommons/__init__.py
daemoncommons/daemon.py
carpi_daemoncommons-0.2.0.dist-info/LICENSE
carpi_daemoncommons-0.2.0.dist-info/METADATA
carpi_daemoncommons-0.2.0.dist-info/WHEEL
carpi_daemoncommons-0.2.0.dist-info/top_level.txt
carpi_daemoncommons-0.2.0.dist-info/RECORD
